.gitignore
LICENSE
MANIFEST.in
Makefile
README.md
pip-requirements.txt
rdlm-daemon.py
setup.py
test-requirements.txt
rdlm/__init__.py
rdlm/__init__.pyc
rdlm/hal.py
rdlm/hello_handler.py
rdlm/lock.py
rdlm/lock_handler.py
rdlm/locks_handler.py
rdlm/main.py
rdlm/options.py
rdlm/request_handler.py
rdlm/resource_handler.py
rdlm/resources_handler.py
rdlm.egg-info/PKG-INFO
rdlm.egg-info/SOURCES.txt
rdlm.egg-info/dependency_links.txt
rdlm.egg-info/requires.txt
rdlm.egg-info/top_level.txt
tests/bomb1.py
tests/bomb2.py
tests/test_auth.py
tests/test_hal.py
tests/test_home.py
tests/test_lock.py