Metadata-Version: 1.1
Name: rdlm
Version: 0.4.2
Summary: RDLM (Restful Distributed Lock Manager) is a lock manager over HTTP build on Tornado
Home-page: https://github.com/thefab/restful-distributed-lock-manager
Author: Fabien MARTY
Author-email: fabien.marty@gmail.com
License: MIT
Download-URL: https://github.com/thefab/restful-distributed-lock-manager
Platform: UNKNOWN
Classifier: Development Status :: 4 - Beta
Classifier: Environment :: Console
Classifier: Intended Audience :: Developers
Classifier: Intended Audience :: Developers
Classifier: Intended Audience :: System Administrators
Classifier: Intended Audience :: System Administrators
Classifier: License :: OSI Approved :: MIT License
Classifier: Operating System :: MacOS :: MacOS X
Classifier: Operating System :: POSIX
Classifier: Operating System :: Unix
Classifier: Programming Language :: Python :: 2.6
Classifier: Programming Language :: Python :: 2.7
Classifier: Programming Language :: Python :: 3.2
Classifier: Programming Language :: Python :: 3.3
Classifier: Topic :: Utilities
Classifier: Topic :: System :: Distributed Computing
Classifier: Topic :: Software Development
Classifier: Topic :: Internet :: WWW/HTTP :: HTTP Servers
Classifier: Topic :: Internet :: WWW/HTTP :: Dynamic Content
